odoo/addons/stock_warehouse_analytic/README.rst
odoo/addons/stock_warehouse_analytic/__init__.py
odoo/addons/stock_warehouse_analytic/__manifest__.py
odoo/addons/stock_warehouse_analytic/i18n/es.po
odoo/addons/stock_warehouse_analytic/i18n/it.po
odoo/addons/stock_warehouse_analytic/i18n/stock_warehouse_analytic.pot
odoo/addons/stock_warehouse_analytic/models/__init__.py
odoo/addons/stock_warehouse_analytic/models/stock_warehouse.py
odoo/addons/stock_warehouse_analytic/readme/CONTRIBUTORS.rst
odoo/addons/stock_warehouse_analytic/readme/DESCRIPTION.rst
odoo/addons/stock_warehouse_analytic/static/description/icon.png
odoo/addons/stock_warehouse_analytic/static/description/index.html
odoo/addons/stock_warehouse_analytic/views/stock_warehouse.xml
odoo14_addon_stock_warehouse_analytic-14.0.1.0.1.dev7.dist-info/METADATA
odoo14_addon_stock_warehouse_analytic-14.0.1.0.1.dev7.dist-info/WHEEL
odoo14_addon_stock_warehouse_analytic-14.0.1.0.1.dev7.dist-info/top_level.txt
odoo14_addon_stock_warehouse_analytic-14.0.1.0.1.dev7.dist-info/RECORD
